UseProlog256/__init__.py
UseProlog256-1.0.1.dist-info/METADATA
UseProlog256-1.0.1.dist-info/WHEEL
UseProlog256-1.0.1.dist-info/top_level.txt
UseProlog256-1.0.1.dist-info/RECORD
