Metadata-Version: 2.1
Name: UseProlog256
Version: 1.0.1
Summary: This is my first module
Home-page: https://github.com/Ivan101002/TestRepOnPython
Author: IvanP
Author-email: I.popovich2002@gmail.com
Keywords: example python prolog
Classifier: Programming Language :: Python :: 3.11
Classifier: License :: OSI Approved :: MIT License
Classifier: Operating System :: OS Independent
Requires-Python: >=3.7
Requires-Dist: requests >=2.25.1
